{"accessLevel":"public","landingPage":"https://data.medicaid.gov/d/8vcd-dnq9","bureauCode":["009:00"],"issued":"2016-11-29","@type":"dcat:Dataset","modified":"2017-05-22","keyword":[{"created":"2017-12-23T02:09:52.406Z","title":"enrollment strategies","modified":"2017-12-23T02:09:52.406Z","identifier":"enrollment-strategies","interra":{"id":"enrollment-strategies"}}],"contactPoint":{"@type":"vcard:Contact","fn":"<Nobody>","hasEmail":"mailto:Medicaid.gov@cms.hhs.gov"},"publisher":{"@type":"org:Organization","name":"data.medicaid.gov","interra":{"id":"datamedicaidgov","source":"datamedicaidgov"},"image":"http://healthdata-example.interra.io/media/medicaid-logo.png","identifier":"1dc0b243-2816-4664-b82f-45b799e2943d","created":"2017-12-22","modified":"2017-12-22"},"identifier":"https://data.medicaid.gov/api/views/8vcd-dnq9","description":"States may rely on eligibility information from \"Express Lane\" agency programs to streamline and simplify enrollment and renewal in Medicaid and CHIP. Express Lane agencies may include Supplemental Nutrition Assistance Program (SNAP), School Lunch programs, Temporary Assistance for Needy Families, Head Start, and the Women, infant, and children's program (WIC) , among others. States can also use state income tax data to determine Medicaid and CHIP eligibility for children.","title":"Express Lane Eligibility for Medicaid and CHIP Coverage","programCode":["009:076"],"distribution":[{"@type":"dcat:Distribution","downloadURL":"https://data.medicaid.gov/api/views/8vcd-dnq9/rows.csv?accessType=DOWNLOAD","mediaType":"text/csv","title":"d7f5b53a-b5fd-4c7e-8482-68a1f6bbd1ad","interra":{"id":"d7f5b53a-b5fd-4c7e-8482-6","source":"datamedicaidgov"},"identifier":"54996adb-4433-4a7a-bf99-5dfe28307a98","created":"2017-12-22","modified":"2017-12-22","format":"csv"},{"@type":"dcat:Distribution","downloadURL":"https://data.medicaid.gov/api/views/8vcd-dnq9/rows.rdf?accessType=DOWNLOAD","mediaType":"application/rdf+xml","title":"fc7411f2-ce0f-4106-8aed-771be068ace8","interra":{"id":"fc7411f2-ce0f-4106-8aed-7","source":"datamedicaidgov"},"identifier":"c8c1f1cf-bd87-42b8-b273-14c1fab52492","created":"2017-12-22","modified":"2017-12-22","format":"rdf+xml"},{"@type":"dcat:Distribution","downloadURL":"https://data.medicaid.gov/api/views/8vcd-dnq9/rows.json?accessType=DOWNLOAD","mediaType":"application/json","title":"ff97dfd0-df0b-4dd9-a114-ef597a39f32e","interra":{"id":"ff97dfd0-df0b-4dd9-a114-e","source":"datamedicaidgov"},"identifier":"1ff8af5d-b9c2-42bc-968c-4f58dc8a35d3","created":"2017-12-22","modified":"2017-12-22","format":"json"},{"@type":"dcat:Distribution","downloadURL":"https://data.medicaid.gov/api/views/8vcd-dnq9/rows.xml?accessType=DOWNLOAD","mediaType":"application/xml","title":"08eb9b26-118c-4a7e-b35e-3abe3698ca8b","interra":{"id":"08eb9b26-118c-4a7e-b35e-3","source":"datamedicaidgov"},"identifier":"906dde9f-86db-46cc-b4ab-9d67f3e85866","created":"2017-12-22","modified":"2017-12-22","format":"xml"}],"license":"https://www.usa.gov/government-works","theme":[{"created":"2017-11-27T19:39:57.028Z","title":"Eligibility","modified":"2017-11-27T19:39:57.028Z","identifier":"eligibility","interra":{"id":"eligibility"}}],"publisher.name":["Centers for Medicare & Medicaid Services"],"interra":{"id":"express-lane-eligibility-","source":"datamedicaidgov"}}
