{"accessLevel":"public","landingPage":"https://data.cityofboston.gov/d/ekiy-2qmz","issued":"2012-12-05","@type":"dcat:Dataset","modified":"2014-10-28","keyword":[{"created":"2017-11-27T19:39:52.151Z","title":"food","modified":"2017-11-27T19:39:52.151Z","identifier":"food","interra":{"id":"food"}},{"created":"2017-11-27T19:39:44.194Z","title":"food initiatives","modified":"2017-11-27T19:39:44.194Z","identifier":"food-initiatives","interra":{"id":"food-initiatives"}},{"created":"2017-11-27T19:39:44.145Z","title":"corner stores","modified":"2017-11-27T19:39:44.145Z","identifier":"corner-stores","interra":{"id":"corner-stores"}},{"created":"2017-11-27T19:39:51.485Z","title":"public health","modified":"2017-11-27T19:39:51.485Z","identifier":"public-health","interra":{"id":"public-health"}},{"created":"2017-11-27T19:39:44.196Z","title":"food access","modified":"2017-11-27T19:39:44.196Z","identifier":"food-access","interra":{"id":"food-access"}},{"created":"2017-11-27T19:39:44.180Z","title":"food security","modified":"2017-11-27T19:39:44.180Z","identifier":"food-security","interra":{"id":"food-security"}},{"created":"2017-11-27T19:39:44.148Z","title":"healthy food","modified":"2017-11-27T19:39:44.148Z","identifier":"healthy-food","interra":{"id":"healthy-food"}}],"contactPoint":{"@type":"vcard:Contact","fn":"<Nobody>","hasEmail":"mailto:genevieve.goldleaf@cityofboston.gov"},"publisher":{"@type":"org:Organization","name":"data.cityofboston.gov","interra":{"id":"datacityofbostongov-0","source":"datacityofbostongov"},"identifier":"95efab0e-8765-49e9-844a-cf2ce4331c82","created":"2017-11-27","modified":"2017-11-27"},"identifier":"https://data.cityofboston.gov/api/views/ekiy-2qmz","description":"Corner stores and bodegas participating in the Healthy Corner Stores Initiative sponsored by the Boston Public Health Commission, and other community health center healthy corner store project locations. Accurate as of December 2012: please contact with corrections and updates!","title":"Healthy Corner Stores","distribution":[{"@type":"dcat:Distribution","downloadURL":"https://data.cityofboston.gov/api/views/ekiy-2qmz/rows.csv?accessType=DOWNLOAD","mediaType":"text/csv","title":"f802d10f-e085-4c07-a7aa-0fdc359e6727","interra":{"id":"f802d10f-e085-4c07-a7aa-0","source":"datacityofbostongov"},"identifier":"8c51d3c6-90ca-4f64-856d-1fc6fc5b951c","created":"2017-11-27","modified":"2017-11-27","format":"csv"},{"@type":"dcat:Distribution","downloadURL":"https://data.cityofboston.gov/api/views/ekiy-2qmz/rows.rdf?accessType=DOWNLOAD","mediaType":"application/rdf+xml","title":"1323bf41-b761-445d-bbdf-c7c5ded83184","interra":{"id":"1323bf41-b761-445d-bbdf-c","source":"datacityofbostongov"},"identifier":"4d445a6a-c104-4fe7-93c5-c5fec432ee3b","created":"2017-11-27","modified":"2017-11-27","format":"rdf+xml"},{"@type":"dcat:Distribution","downloadURL":"https://data.cityofboston.gov/api/views/ekiy-2qmz/rows.json?accessType=DOWNLOAD","mediaType":"application/json","title":"24230dec-4b96-443f-8a22-ffba2a6501f5","interra":{"id":"24230dec-4b96-443f-8a22-f","source":"datacityofbostongov"},"identifier":"7fa41aec-4d92-47ae-81d2-d5374c794c3a","created":"2017-11-27","modified":"2017-11-27","format":"json"},{"@type":"dcat:Distribution","downloadURL":"https://data.cityofboston.gov/api/views/ekiy-2qmz/rows.xml?accessType=DOWNLOAD","mediaType":"application/xml","title":"a44beadb-6827-4f0e-8892-15015f4a55d6","interra":{"id":"a44beadb-6827-4f0e-8892-1","source":"datacityofbostongov"},"identifier":"333dc50a-bb63-4ea7-b31a-ce314a2633cb","created":"2017-11-27","modified":"2017-11-27","format":"xml"}],"license":"http://creativecommons.org/publicdomain/zero/1.0/legalcode","theme":[{"created":"2017-11-27T19:39:52.725Z","title":"Health","modified":"2017-11-27T19:39:52.725Z","identifier":"health","icon":"heart-beat","interra":{"id":"health"}}],"publisher.name":"City of Boston","programCode":["000:000"],"bureauCode":["000:00"],"interra":{"id":"healthy-corner-stores","source":"datacityofbostongov"}}
