{"accessLevel":"public","landingPage":"https://data.cdc.gov/d/rg8a-czmp","bureauCode":["009:00"],"issued":"2017-08-15","@type":"dcat:Dataset","modified":"2017-08-22","keyword":[{"created":"2017-12-23T02:09:47.384Z","title":"birth rate","modified":"2017-12-23T02:09:47.384Z","identifier":"birth-rate","interra":{"id":"birth-rate"}},{"created":"2017-12-23T02:09:54.372Z","title":"women","modified":"2017-12-23T02:09:54.372Z","identifier":"women","interra":{"id":"women"}},{"created":"2017-12-23T02:09:31.062Z","title":"united states","modified":"2017-12-23T02:09:31.062Z","identifier":"united-states","interra":{"id":"united-states"}},{"created":"2017-12-23T02:09:31.062Z","title":"nchs","modified":"2017-12-23T02:09:31.062Z","identifier":"nchs","interra":{"id":"nchs"}}],"contactPoint":{"@type":"vcard:Contact","fn":"National Center for Health Statistics","hasEmail":"mailto:nchsdata@cdc.gov"},"publisher":{"@type":"org:Organization","name":"National Center for Health Statistics","interra":{"id":"national-center-for-healt","source":"datacdcgov"},"image":"http://healthdata-example.interra.io/media/chhslogo.png","description":"The mission of the National Center for Health Statistics (NCHS) is to provide statistical information that will guide actions and policies to improve the health of the American people. As the Nation's principal health statistics agency, NCHS leads the way with accurate, relevant, and timely data.","identifier":"7d48924c-4f85-4780-b990-edc620c889be","created":"2017-12-22","modified":"2017-12-22"},"identifier":"https://data.cdc.gov/api/views/rg8a-czmp","description":"http://blogs.cdc.gov/nchs-data-visualization/us-natality-trends/","title":"NCHS - Birth Rates for Women Aged 15-17, 17-18, and 15-19: United States, 1960-2015","programCode":["009:020"],"distribution":[{"@type":"dcat:Distribution","downloadURL":"https://data.cdc.gov/api/views/rg8a-czmp/rows.csv?accessType=DOWNLOAD","mediaType":"text/csv","title":"88d8c71b-98df-4b44-9bc4-f49a8c891110","interra":{"id":"88d8c71b-98df-4b44-9bc4-f","source":"datacdcgov"},"identifier":"02af3204-15bf-4529-b814-c78c5fbf5f8c","created":"2017-12-22","modified":"2017-12-22","format":"csv"},{"@type":"dcat:Distribution","downloadURL":"https://data.cdc.gov/api/views/rg8a-czmp/rows.rdf?accessType=DOWNLOAD","mediaType":"application/rdf+xml","title":"f587c9f0-d533-4f17-87ac-d41acbc296a7","interra":{"id":"f587c9f0-d533-4f17-87ac-d","source":"datacdcgov"},"identifier":"3b8dcff1-9c74-4492-ad22-e561d0e0f832","created":"2017-12-22","modified":"2017-12-22","format":"rdf+xml"},{"@type":"dcat:Distribution","downloadURL":"https://data.cdc.gov/api/views/rg8a-czmp/rows.json?accessType=DOWNLOAD","mediaType":"application/json","title":"ea8175f6-1614-4e75-af9c-da89216b9f33","interra":{"id":"ea8175f6-1614-4e75-af9c-d","source":"datacdcgov"},"identifier":"7197654d-da25-466a-83a1-7e49df38ac03","created":"2017-12-22","modified":"2017-12-22","format":"json"},{"@type":"dcat:Distribution","downloadURL":"https://data.cdc.gov/api/views/rg8a-czmp/rows.xml?accessType=DOWNLOAD","mediaType":"application/xml","title":"40aa1613-e625-4f3a-9a69-3ca2070f86a4","interra":{"id":"40aa1613-e625-4f3a-9a69-3","source":"datacdcgov"},"identifier":"e182e094-413c-4663-a274-3491e98a6527","created":"2017-12-22","modified":"2017-12-22","format":"xml"}],"theme":[{"created":"2017-11-27T19:39:37.129Z","title":"NCHS","modified":"2017-11-27T19:39:37.129Z","identifier":"nchs","interra":{"id":"nchs"}}],"publisher.name":["Centers for Disease Control and Prevention"],"license":"http://opendefinition.org/licenses/odc-odbl/","interra":{"id":"nchs-birth-rates-for-wome","source":"datacdcgov"}}
