{"accessLevel":"public","landingPage":"https://data.cdc.gov/d/e9r5-5hjr","bureauCode":["009:00"],"issued":"2015-08-10","@type":"dcat:Dataset","modified":"2015-08-27","keyword":[{"created":"2017-12-23T02:09:31.240Z","title":"chikungunya","modified":"2017-12-23T02:09:31.240Z","identifier":"chikungunya","interra":{"id":"chikungunya"}},{"created":"2017-12-23T02:09:31.241Z","title":"americas","modified":"2017-12-23T02:09:31.241Z","identifier":"americas","interra":{"id":"americas"}},{"created":"2017-12-23T02:09:31.242Z","title":"paho","modified":"2017-12-23T02:09:31.242Z","identifier":"paho","interra":{"id":"paho"}}],"contactPoint":{"@type":"vcard:Contact","fn":"CDC INFO","hasEmail":"mailto:cdcinfo@cdc.gov"},"publisher":{"@type":"org:Organization","name":"data.cdc.gov","image":"http://healthdata-example.interra.io/media/cdc-logo.jpg","interra":{"id":"datacdcgov","source":"datacdcgov"},"identifier":"5311e57e-0c6a-4795-a83f-4fa2da2c4f77","created":"2017-12-22","modified":"2017-12-22"},"identifier":"https://data.cdc.gov/api/views/e9r5-5hjr","description":"Derived from Pan American Health Organization reports: http://www.paho.org/hq/index.php?option=com_topics&view=article&id=343&Itemid=40931","title":"New Chikungunya Cases Reported in the Americas","programCode":["009:020"],"distribution":[{"@type":"dcat:Distribution","downloadURL":"https://data.cdc.gov/api/views/e9r5-5hjr/rows.csv?accessType=DOWNLOAD","mediaType":"text/csv","title":"3edc317f-66e1-4b57-89ef-a3c1a29c8cab","interra":{"id":"3edc317f-66e1-4b57-89ef-a","source":"datacdcgov"},"identifier":"3a89e9ff-f774-45a9-9cbf-baa0a185998f","created":"2017-12-22","modified":"2017-12-22","format":"csv"},{"@type":"dcat:Distribution","downloadURL":"https://data.cdc.gov/api/views/e9r5-5hjr/rows.rdf?accessType=DOWNLOAD","mediaType":"application/rdf+xml","title":"a33e477e-b21c-4e80-bbf3-9bfe72e64867","interra":{"id":"a33e477e-b21c-4e80-bbf3-9","source":"datacdcgov"},"identifier":"76046843-0356-4e6a-9c76-3a1b50264d52","created":"2017-12-22","modified":"2017-12-22","format":"rdf+xml"},{"@type":"dcat:Distribution","downloadURL":"https://data.cdc.gov/api/views/e9r5-5hjr/rows.json?accessType=DOWNLOAD","mediaType":"application/json","title":"1d7ca17d-e420-457e-892f-47fdc7465c24","interra":{"id":"1d7ca17d-e420-457e-892f-4","source":"datacdcgov"},"identifier":"a19ce2c7-82a3-4c37-bdcf-f099946c244d","created":"2017-12-22","modified":"2017-12-22","format":"json"},{"@type":"dcat:Distribution","downloadURL":"https://data.cdc.gov/api/views/e9r5-5hjr/rows.xml?accessType=DOWNLOAD","mediaType":"application/xml","title":"c0eb7480-a86b-42aa-bcdb-3a48473d27c1","interra":{"id":"c0eb7480-a86b-42aa-bcdb-3","source":"datacdcgov"},"identifier":"2674e487-4365-49fc-8851-efa5e4818604","created":"2017-12-22","modified":"2017-12-22","format":"xml"}],"theme":[{"created":"2017-11-27T19:39:38.579Z","title":"Health Statistics","modified":"2017-11-27T19:39:38.579Z","identifier":"health-statistics","interra":{"id":"health-statistics"}}],"publisher.name":["Centers for Disease Control and Prevention"],"license":"http://opendefinition.org/licenses/odc-odbl/","interra":{"id":"new-chikungunya-cases-rep","source":"datacdcgov"}}
