{"accessLevel":"public","landingPage":"https://data.sfgov.org/d/cne3-h93g","issued":"2016-03-25","@type":"dcat:Dataset","modified":"2016-03-25","keyword":[{"created":"2017-11-27T19:39:43.735Z","title":"climate change","modified":"2017-11-27T19:39:43.735Z","identifier":"climate-change","interra":{"id":"climate-change"}},{"created":"2017-11-27T19:39:43.736Z","title":"flood","modified":"2017-11-27T19:39:43.736Z","identifier":"flood","interra":{"id":"flood"}},{"created":"2017-11-27T19:39:43.737Z","title":"sea level rise","modified":"2017-11-27T19:39:43.737Z","identifier":"sea-level-rise","interra":{"id":"sea-level-rise"}},{"created":"2017-11-27T19:39:43.737Z","title":"health impacts","modified":"2017-11-27T19:39:43.737Z","identifier":"health-impacts","interra":{"id":"health-impacts"}},{"created":"2017-11-27T19:39:43.738Z","title":"health assessment","modified":"2017-11-27T19:39:43.738Z","identifier":"health-assessment","interra":{"id":"health-assessment"}},{"created":"2017-11-27T19:39:43.739Z","title":"san francisco climate and health program","modified":"2017-11-27T19:39:43.739Z","identifier":"san-francisco-climate-and","interra":{"id":"san-francisco-climate-and"}},{"created":"2017-11-27T19:39:43.796Z","title":"sfclimatehealth.org","modified":"2017-11-27T19:39:43.796Z","identifier":"sfclimatehealthorg","interra":{"id":"sfclimatehealthorg"}},{"created":"2017-11-27T19:39:43.797Z","title":"community resiliency","modified":"2017-11-27T19:39:43.797Z","identifier":"community-resiliency","interra":{"id":"community-resiliency"}},{"created":"2017-11-27T19:39:51.485Z","title":"public health","modified":"2017-11-27T19:39:51.485Z","identifier":"public-health","interra":{"id":"public-health"}},{"created":"2017-11-27T19:39:43.796Z","title":"sfclimatehealth.org","modified":"2017-11-27T19:39:43.796Z","identifier":"sfclimatehealthorg","interra":{"id":"sfclimatehealthorg"}},{"created":"2017-11-27T19:39:43.800Z","title":"dph","modified":"2017-11-27T19:39:43.800Z","identifier":"dph","interra":{"id":"dph"}}],"contactPoint":{"@type":"vcard:Contact","fn":"<Nobody>","hasEmail":"mailto:datasf.support@sfgov.org"},"publisher":{"@type":"org:Organization","name":"data.sfgov.org","interra":{"id":"datasfgovorg-0","source":"datasfgovorg"},"identifier":"4829315e-f537-449e-9202-e336118dd3ba","created":"2017-11-27","modified":"2017-11-27"},"identifier":"https://data.sfgov.org/api/views/cne3-h93g","description":"The San Francisco Department of Public Health Flood Health Vulnerability Index is a composite index that measures the spatial distribution and relative vulnerability of San Francisco communities to the health impacts of flood inundation and extreme storms. The index is constructed using socioeconomic and demographic, exposure, health, and housing indicators and is intended to serve as a planning tool for health and climate adaptation. Steps for calculating the index can be found in in the \"An Assessment of San Francisco’s Vulnerability to Flooding & Extreme Storms\" located at https://extxfer.sfdph.org/gis/Flooding/SFDPH_FloodHealthVulnerability2016.pdf.\r\n\r\nData dictionary can be found in the attachments section of the metadata.","title":"San Francisco Flood Health Vulnerability","distribution":[{"@type":"dcat:Distribution","downloadURL":"https://data.sfgov.org/api/views/cne3-h93g/rows.csv?accessType=DOWNLOAD","mediaType":"text/csv","title":"890d6932-c649-4eda-af7c-874b365b5210","interra":{"id":"890d6932-c649-4eda-af7c-8","source":"datasfgovorg"},"identifier":"a0c7ed57-f761-4b8c-aa0d-139f5cf947fe","created":"2017-11-27","modified":"2017-11-27","format":"csv"},{"@type":"dcat:Distribution","downloadURL":"https://data.sfgov.org/api/views/cne3-h93g/rows.rdf?accessType=DOWNLOAD","mediaType":"application/rdf+xml","title":"98f6185c-2a57-4cd9-8469-66c1d6d79070","interra":{"id":"98f6185c-2a57-4cd9-8469-6","source":"datasfgovorg"},"identifier":"49a470da-042f-4b56-8a4e-a0310bc42199","created":"2017-11-27","modified":"2017-11-27","format":"rdf+xml"},{"@type":"dcat:Distribution","downloadURL":"https://data.sfgov.org/api/views/cne3-h93g/rows.json?accessType=DOWNLOAD","mediaType":"application/json","title":"9417f0a2-5639-49de-b27a-79184a9c6af2","interra":{"id":"9417f0a2-5639-49de-b27a-7","source":"datasfgovorg"},"identifier":"ca908011-1329-443c-ac83-39b06cd9d617","created":"2017-11-27","modified":"2017-11-27","format":"json"},{"@type":"dcat:Distribution","downloadURL":"https://data.sfgov.org/api/views/cne3-h93g/rows.xml?accessType=DOWNLOAD","mediaType":"application/xml","title":"d2198ac6-ed5c-42e6-95f0-3b5eab7b95f1","interra":{"id":"d2198ac6-ed5c-42e6-95f0-3","source":"datasfgovorg"},"identifier":"a14cda40-1ad4-4bb1-ba18-c89196039cab","created":"2017-11-27","modified":"2017-11-27","format":"xml"}],"license":"http://opendatacommons.org/licenses/pddl/1.0/","theme":[{"created":"2017-11-27T19:39:43.841Z","title":"Health and Social Services","modified":"2017-11-27T19:39:43.841Z","identifier":"health-and-social-service","interra":{"id":"health-and-social-service"}}],"publisher.name":"City of San Francisco","programCode":["000:000"],"bureauCode":["000:00"],"interra":{"id":"san-francisco-flood-healt","source":"datasfgovorg"}}
